zinny_surveys/__init__.py
zinny_surveys/data/surveys/shared/acting.json
zinny_surveys/data/surveys/shared/cinematography.json
zinny_surveys/data/surveys/shared/directoral.json
zinny_surveys/data/surveys/shared/docs.json
zinny_surveys/data/surveys/shared/picture.json
zinny_surveys/data/surveys/shared/picture_extended.json
zinny_surveys/data/surveys/shared/runoff_acting.json
zinny_surveys/data/surveys/shared/runoff_cinematography.json
zinny_surveys/data/surveys/shared/runoff_directoral.json
zinny_surveys/data/surveys/shared/runoff_docs.json
zinny_surveys/data/surveys/shared/runoff_picture.json
zinny_surveys/data/surveys/shared/runoff_vfx.json
zinny_surveys/data/surveys/shared/vfx_basic.json
zinny_surveys/data/surveys/shared/vfx_exhaustive.json
zinny_surveys/data/surveys/shared/vfx_extended.json
zinny_surveys/data/weights/shared/acting_weights.json
zinny_surveys/data/weights/shared/cinematography_weights.json
zinny_surveys/data/weights/shared/directoral_weights.json
zinny_surveys/data/weights/shared/docs_weights.json
zinny_surveys/data/weights/shared/picture_storyteller.json
zinny_surveys/data/weights/shared/picture_technologist.json
zinny_surveys/data/weights/shared/picture_weights.json
zinny_surveys/data/weights/shared/vfx_extended_weights.json
zinny_surveys/data/weights/shared/vfx_weights.json
zinny_surveys-0.1.8.dist-info/LICENSE
zinny_surveys-0.1.8.dist-info/METADATA
zinny_surveys-0.1.8.dist-info/WHEEL
zinny_surveys-0.1.8.dist-info/top_level.txt
zinny_surveys-0.1.8.dist-info/RECORD
