Metadata-Version: 2.1
Name: zinny-surveys
Version: 0.1.8
Summary: Surveys and specifications for rating Motion Picture titles.  Used by Zinny, the movei rating app.
Author: Ryan Laney
License: BSD 3-Clause License
Project-URL: Homepage, https://github.com/RyLaney/zinny-surveys
Project-URL: Issues, https://github.com/RyLaney/zinny-surveys/issues
Keywords: zinny,surveys
Classifier: Programming Language :: Python :: 3
Classifier: License :: OSI Approved :: BSD License
Classifier: Operating System :: OS Independent
Requires-Python: >=3.8
License-File: LICENSE
Provides-Extra: dev
Requires-Dist: pytest; extra == "dev"
Requires-Dist: black; extra == "dev"
